dalle_pytorch_dev/__init__.py
dalle_pytorch_dev/dalle_pytorch.py
dalle_pytorch_dev-0.0.3.dist-info/LICENSE
dalle_pytorch_dev-0.0.3.dist-info/METADATA
dalle_pytorch_dev-0.0.3.dist-info/WHEEL
dalle_pytorch_dev-0.0.3.dist-info/top_level.txt
dalle_pytorch_dev-0.0.3.dist-info/RECORD
