Metadata-Version: 2.1
Name: dalle-pytorch-dev
Version: 0.0.3
Summary: DALL-E - Pytorch
Home-page: https://github.com/lucidrains/dalle-pytorch
Author: Phil Wang
Author-email: lucidrains@gmail.com
License: MIT
Keywords: artificial intelligence,attention mechanism,transformers,text-to-image
Platform: UNKNOWN
Classifier: Development Status :: 4 - Beta
Classifier: Intended Audience :: Developers
Classifier: Topic :: Scientific/Engineering :: Artificial Intelligence
Classifier: License :: OSI Approved :: MIT License
Classifier: Programming Language :: Python :: 3.6
Requires-Dist: einops (>=0.3)
Requires-Dist: torch (>=1.6)
Requires-Dist: x-transformers
